VectLight/__init__.py
vectlight-0.0.0.dist-info/METADATA
vectlight-0.0.0.dist-info/WHEEL
vectlight-0.0.0.dist-info/licenses/LICENSE
vectlight-0.0.0.dist-info/RECORD
