Metadata-Version: 2.4
Name: VectLight
Version: 0.0.0
Summary: Vectorial Optics and Photonics Toolbox
License-File: LICENSE
Classifier: License :: OSI Approved :: GNU General Public License v3 or later (GPLv3+)
Classifier: Operating System :: Microsoft :: Windows
Classifier: Programming Language :: Python :: 3
Requires-Python: >=3.10
